{
    "expenses": {
        "total_amount": 66521.59,
        "main": [
            {
                "Категория": "Услуги банка",
                "потрачено": 59.0
            },
            {
                "Категория": "Различные товары",
                "потрачено": 2330.0
            },
            {
                "Категория": "Ж/д билеты",
                "потрачено": 2012.2
            },
            {
                "Категория": "Супермаркеты",
                "потрачено": 9337.79
            },
            {
                "Категория": "Фастфуд",
                "потрачено": 3310.8
            },
            {
                "Категория": "Сувениры",
                "потрачено": 290.0
            },
            {
                "Категория": "Связь",
                "потрачено": 5700.0
            },
            {
                "Категория": "Книги",
                "потрачено": 5.0
            },
            {
                "Категория": "Аптеки",
                "потрачено": 6151.1
            },
            {
                "Категория": "Транспорт",
                "потрачено": 1262.0
            },
            {
                "Категория": "НКО",
                "потрачено": 5.18
            },
            {
                "Категория": "Переводы",
                "потрачено": 6590.62
            },
            {
                "Категория": "Сервис",
                "потрачено": 185.0
            },
            {
                "Категория": "Кино",
                "потрачено": 409.0
            },
            {
                "Категория": "Другое",
                "потрачено": 9400.87
            },
            {
                "Категория": "Наличные",
                "потрачено": 300.0
            },
            {
                "Категория": "Дом и ремонт",
                "потрачено": 240.0
            }
        ]
    },
    "transfers_and_cash": [
        {
            "category": "Наличные",
            "amount": 300.0
        },
        {
            "category": "Переводы",
            "amount": 300.0
        }
    ],
    "income": [
        {
            "category": "Пополнения",
            "amount": 10000.0
        },
        {
            "category": "Проценты на остаток",
            "amount": 0
        },
        {
            "category": "Кэшбэк за обычные покупки",
            "amount": 0
        }
    ],
    "currency_rate": [
        {
            "currency": "USD",
            "rate": "80.244696"
        },
        {
            "currency": "EUR",
            "rate": "90.981617"
        }
    ],
    "stock_rates": [
        {
            "ticker": "AAPL",
            "price in USD": 200.21
        },
        {
            "ticker": "AMZN",
            "price in USD": 206.02
        },
        {
            "ticker": "GOOGL",
            "price in USD": 172.9
        },
        {
            "ticker": "MSFT",
            "price in USD": 460.69
        },
        {
            "ticker": "TSLA",
            "price in USD": 362.89
        }
    ]
}